forgeprecommit/__init__.py
forgeprecommit/cli.py
forgeprecommit/install.py
forge_precommit-1.3.0.dist-info/LICENSE
forge_precommit-1.3.0.dist-info/METADATA
forge_precommit-1.3.0.dist-info/WHEEL
forge_precommit-1.3.0.dist-info/entry_points.txt
forge_precommit-1.3.0.dist-info/RECORD
